uwrapper/__init__.py
uwrapper/scripts/__init__.py
uwrapper/scripts/services/__init__.py
uwrapper/scripts/services/instrument_files.py
uwrapper/scripts/services/login.py
uwrapper/scripts/src/__init__.py
uwrapper-0.0.8.dist-info/METADATA
uwrapper-0.0.8.dist-info/WHEEL
uwrapper-0.0.8.dist-info/top_level.txt
uwrapper-0.0.8.dist-info/RECORD
